cryptotax_summary/__init__.py
cryptotax_summary/crypto_summary.py
cryptotax_summary-0.1.3.dist-info/LICENSE
cryptotax_summary-0.1.3.dist-info/METADATA
cryptotax_summary-0.1.3.dist-info/WHEEL
cryptotax_summary-0.1.3.dist-info/entry_points.txt
cryptotax_summary-0.1.3.dist-info/top_level.txt
cryptotax_summary-0.1.3.dist-info/RECORD
