Metadata-Version: 2.2
Name: cryptotax_summary
Version: 0.1.3
Summary: A library to summarize crypto transactions for tax reporting
Home-page: https://github.com/whyabhinay/cryptotax_summary
Author: Your Name
Author-email: Abhinay.Yarlagadda@gmail.com
License: MIT
Classifier: Programming Language :: Python :: 3
Classifier: License :: OSI Approved :: MIT License
Classifier: Operating System :: OS Independent
Requires-Python: >=3.8
License-File: LICENSE
Requires-Dist: pandas
Dynamic: author
Dynamic: author-email
Dynamic: classifier
Dynamic: description
Dynamic: description-content-type
Dynamic: home-page
Dynamic: license
Dynamic: requires-dist
Dynamic: requires-python
Dynamic: summary
